.mina/qqguild-tencent.toml
avilla/qqguild/tencent/__init__.py
avilla/qqguild/tencent/account.py
avilla/qqguild/tencent/audit/__init__.py
avilla/qqguild/tencent/audit/event.py
avilla/qqguild/tencent/audit/metadata.py
avilla/qqguild/tencent/audit/store.py
avilla/qqguild/tencent/collector/__init__.py
avilla/qqguild/tencent/collector/connection.py
avilla/qqguild/tencent/connection/__init__.py
avilla/qqguild/tencent/connection/base.py
avilla/qqguild/tencent/connection/util.py
avilla/qqguild/tencent/connection/ws_client.py
avilla/qqguild/tencent/const.py
avilla/qqguild/tencent/element.py
avilla/qqguild/tencent/exception.py
avilla/qqguild/tencent/perform/__init__.py
avilla/qqguild/tencent/perform/action/__init__.py
avilla/qqguild/tencent/perform/action/channel.py
avilla/qqguild/tencent/perform/action/guild.py
avilla/qqguild/tencent/perform/action/member.py
avilla/qqguild/tencent/perform/action/message.py
avilla/qqguild/tencent/perform/action/role.py
avilla/qqguild/tencent/perform/context.py
avilla/qqguild/tencent/perform/event/__init__.py
avilla/qqguild/tencent/perform/event/audit.py
avilla/qqguild/tencent/perform/event/message.py
avilla/qqguild/tencent/perform/event/metadata.py
avilla/qqguild/tencent/perform/event/relationship.py
avilla/qqguild/tencent/perform/message/deserialize.py
avilla/qqguild/tencent/perform/message/serialize.py
avilla/qqguild/tencent/perform/query.py
avilla/qqguild/tencent/perform/resource_fetch.py
avilla/qqguild/tencent/protocol.py
avilla/qqguild/tencent/resource.py
avilla/qqguild/tencent/role/__init__.py
avilla/qqguild/tencent/role/capability.py
avilla/qqguild/tencent/role/metadata.py
avilla/qqguild/tencent/service.py
avilla/qqguild/tencent/utils.py
avilla_qqguild_tencent-1.0.0a7.dist-info/METADATA
avilla_qqguild_tencent-1.0.0a7.dist-info/WHEEL
avilla_qqguild_tencent-1.0.0a7.dist-info/licenses/LICENSE
avilla_qqguild_tencent-1.0.0a7.dist-info/RECORD
