Metadata-Version: 2.1
Name: avilla-qqguild-tencent
Version: 1.0.0a7
Home-page: https://github.com/GraiaProject/Avilla
Author-Email: RF-Tar-Railt <rf_tar_railt@qq.com>
License: MIT
Project-URL: Homepage, https://github.com/GraiaProject/Avilla
Project-URL: Repository, https://github.com/GraiaProject/Avilla
Requires-Python: >=3.9
Requires-Dist: aiohttp>=3.8.1
